<?xml version="1.0" encoding="utf-8"?>
<root type="0" typeName="View" time="0" x="0" y="0" width="480" height="800" visible="true" fillParentWidth="true" fillParentHeight="true" nodeAlign="8"><ending_win_dialog_full_screen_bg type="1" typeName="Image" time="11499309" x="0" y="0" width="480" height="800" visible="true" fillParentWidth="true" fillParentHeight="true" nodeAlign="8" file="drawable/blank.png" packFile="" gridLeft="1" gridRight="1" gridTop="1" gridBottom="1"/><ending_win_content_view type="0" typeName="View" time="11500965" x="0" y="-200" width="478" height="226" visible="true" fillParentWidth="false" fillParentHeight="false" nodeAlign="0"><ending_win_dialog_bg type="1" typeName="Image" time="11500981" x="0" y="0" width="480" height="630" visible="true" fillParentWidth="false" fillParentHeight="false" nodeAlign="8" file="dialog/dialog_resize_bg.png" packFile="" gridLeft="64" gridRight="64" gridTop="64" gridBottom="64"/><ending_win_chest1 type="1" typeName="Image" time="19966437" x="15" y="310" width="145" height="145" visible="true" fillParentWidth="false" fillParentHeight="false" nodeAlign="8" file="drawable/ending_reward_bg.png" packFile="" gridLeft="32" gridRight="32" gridTop="32" gridBottom="32"><ending_win_tips1 type="4" typeName="Text" time="19966610" x="0" y="105" width="150" height="0" visible="true" fillParentWidth="false" fillParentHeight="false" nodeAlign="8" fontSize="24" textAlign="19966610" color="0x9EDFFE" string="生命X1"/><ending_win_chest1_texture type="1" typeName="Image" time="20488008" x="10" y="0" width="128" height="130" visible="true" fillParentWidth="false" fillParentHeight="false" nodeAlign="8" file="drawable/ending_chest_texture.png" packFile="" gridLeft="0" gridRight="0" gridTop="0" gridBottom="0"/></ending_win_chest1><ending_win_chest2 type="1" typeName="Image" time="19966667" x="165" y="310" width="145" height="145" visible="true" fillParentWidth="false" fillParentHeight="false" nodeAlign="8" file="drawable/ending_reward_bg.png" packFile="" gridLeft="32" gridRight="32" gridTop="32" gridBottom="32"><ending_win_tips2 type="4" typeName="Text" time="19966749" x="0" y="105" width="150" height="0" visible="true" fillParentWidth="false" fillParentHeight="false" nodeAlign="8" fontSize="24" textAlign="19966749" color="0x9EDFFE" string="悔棋X3"/><ending_win_chest2_texture type="1" typeName="Image" time="20488489" x="10" y="0" width="0" height="0" visible="true" fillParentWidth="false" fillParentHeight="false" nodeAlign="8" file="drawable/endgame_undo_icon.png" packFile="" gridLeft="0" gridRight="0" gridTop="0" gridBottom="0"/></ending_win_chest2><ending_win_chest3 type="1" typeName="Image" time="19966805" x="315" y="310" width="145" height="145" visible="true" fillParentWidth="false" fillParentHeight="false" nodeAlign="8" file="drawable/ending_reward_bg.png" packFile="" gridLeft="32" gridRight="32" gridTop="32" gridBottom="32"><ending_win_tips3 type="4" typeName="Text" time="19966874" x="0" y="105" width="150" height="0" visible="true" fillParentWidth="false" fillParentHeight="false" nodeAlign="8" fontSize="24" textAlign="19966874" color="0x9EDFFE" string="提示X5"/><ending_win_chest3_texture type="1" typeName="Image" time="20488648" x="10" y="0" width="0" height="0" visible="true" fillParentWidth="false" fillParentHeight="false" nodeAlign="8" file="drawable/ending_reborn_img.png" packFile="" gridLeft="0" gridRight="0" gridTop="0" gridBottom="0"/></ending_win_chest3><ending_win_chest_tips type="4" typeName="Text" time="20489038" x="0" y="466" width="480" height="0" visible="true" fillParentWidth="false" fillParentHeight="false" nodeAlign="8" fontSize="24" textAlign="20489038" color="0x9EDFFE" string="恭喜您获得一次免费抽奖的机会！"/><ending_line_texture type="1" typeName="Image" time="20489773" x="12" y="532" width="453" height="3" visible="true" fillParentWidth="false" fillParentHeight="false" nodeAlign="8" file="dialog/horizontal_line.png" packFile="" gridLeft="0" gridRight="0" gridTop="0" gridBottom="0"/><endging_win_result_texture type="1" typeName="Image" time="20490271" x="0" y="35" width="478" height="226" visible="true" fillParentWidth="false" fillParentHeight="false" nodeAlign="8" file="drawable/ending_win_texture.png" packFile="" gridLeft="0" gridRight="0" gridTop="0" gridBottom="0"/><ending_win_people_tips_bg type="1" typeName="Image" time="20692076" x="9" y="167" width="159" height="93" visible="true" fillParentWidth="false" fillParentHeight="false" nodeAlign="8" file="drawable/ending_win_play_tips_bg.png" packFile="" gridLeft="0" gridRight="0" gridTop="0" gridBottom="0"><ending_win_people_tips_tips type="4" typeName="Text" time="20761166" x="22" y="11" width="96" height="24" visible="true" fillParentWidth="false" fillParentHeight="false" nodeAlign="8" fontSize="24" textAlign="20761166" color="0xFFFFFF" string="领先全国"/><ending_win_people_tips_text type="4" typeName="Text" time="20761429" x="13" y="38" width="120" height="24" visible="true" fillParentWidth="false" fillParentHeight="false" nodeAlign="8" fontSize="24" textAlign="20761429" color="0xFFFFFF" string="100%的玩家"/></ending_win_people_tips_bg><ending_win_text_texture type="1" typeName="Image" time="22227603" x="175" y="279" width="127" height="31" visible="true" fillParentWidth="false" fillParentHeight="false" nodeAlign="8" file="drawable/ending_win_text_texture.png" packFile="" gridLeft="0" gridRight="0" gridTop="0" gridBottom="0"/><ending_win_cancel_btn type="2" typeName="Button" time="24808694" x="426" y="26" width="36" height="36" visible="true" fillParentWidth="false" fillParentHeight="false" nodeAlign="8" file="dialog/btn_close_up.png" file2="dialog/btn_close_dow.png" packFile="" gridLeft="0" gridRight="0" gridTop="0" gridBottom="0"/><ending_win_share_btn type="2" typeName="Button" time="24809208" x="50" y="570" width="180" height="75" visible="true" fillParentWidth="false" fillParentHeight="false" nodeAlign="8" file="dialog/btn_pos_up.png" file2="dialog/btn_pos_down.png" packFile="" gridLeft="64" gridRight="64" gridTop="0" gridBottom="0"><ending_win_share_text type="4" typeName="Text" time="24809267" x="0" y="0" width="170" height="70" visible="true" fillParentWidth="false" fillParentHeight="false" nodeAlign="8" fontSize="30" textAlign="24809267" color="0x000000" string="分享"/></ending_win_share_btn><ending_win_next_btn type="2" typeName="Button" time="24809332" x="262" y="569" width="180" height="75" visible="true" fillParentWidth="false" fillParentHeight="false" nodeAlign="8" file="dialog/btn_pos_up.png" file2="dialog/btn_pos_down.png" packFile="" gridLeft="64" gridRight="64" gridTop="0" gridBottom="0"><ending_win_next_text type="4" typeName="Text" time="24809478" x="0" y="0" width="170" height="70" visible="true" fillParentWidth="false" fillParentHeight="false" nodeAlign="8" fontSize="30" textAlign="24809478" color="0x000000" string="下一关"/></ending_win_next_btn></ending_win_content_view></root>
