<?xml version="1.0" encoding="utf-8"?>
<root type="0" typeName="View" time="0" x="0" y="0" width="0" height="0" visible="true" fillParentWidth="true" fillParentHeight="true" nodeAlign="8"><bg type="1" typeName="Image" time="97936054" x="0" y="-100" width="720" height="1189" visible="true" fillParentWidth="true" fillParentHeight="false" nodeAlign="5" file="common/background/dialog_bg_1.png" packFile="" gridLeft="128" gridRight="128" gridTop="128" gridBottom="128"><title type="4" typeName="Text" time="97936150" x="0" y="-4" width="200" height="150" visible="true" fillParentWidth="false" fillParentHeight="false" nodeAlign="1" fontSize="46" textAlign="0" color="0x505050" string="未知"/><bottom_edit type="0" typeName="View" time="97936223" x="0" y="100" width="200" height="144" visible="true" fillParentWidth="true" fillParentHeight="false" nodeAlign="5"><Image2 type="1" typeName="Image" time="97936251" x="0" y="2" width="640" height="19" visible="true" fillParentWidth="false" fillParentHeight="false" nodeAlign="1" file="common/decoration/line.png" packFile="" gridLeft="0" gridRight="0" gridTop="0" gridBottom="0"/><input_bg type="1" typeName="Image" time="97936299" x="-65" y="8" width="486" height="62" visible="true" fillParentWidth="false" fillParentHeight="false" nodeAlign="0" file="common/background/input_bg_2.png" packFile="" gridLeft="33" gridRight="33" gridTop="31" gridBottom="31"><msg_edit type="6" typeName="EditText" time="97950707" x="13" y="-1" width="458" height="50" visible="true" fillParentWidth="false" fillParentHeight="false" nodeAlign="7" fontSize="32" textAlign="7" color="0x505050" string=""/></input_bg><send_btn type="2" typeName="Button" time="97936456" x="250" y="8" width="128" height="58" visible="true" fillParentWidth="false" fillParentHeight="false" nodeAlign="0" file="common/button/dialog_btn_3_normal.png" file2="common/button/dialog_btn_3_press.png" packFile="" gridLeft="0" gridRight="0" gridTop="0" gridBottom="0"><text type="4" typeName="Text" time="97936505" x="0" y="-1" width="200" height="150" visible="true" fillParentWidth="false" fillParentHeight="false" nodeAlign="0" fontSize="32" textAlign="0" color="0xD2E6F0" string="发送"/></send_btn></bottom_edit><content_view type="0" typeName="View" time="97936672" x="0" y="127" width="610" height="810" visible="true" fillParentWidth="false" fillParentHeight="false" nodeAlign="1"/><Image1 type="1" typeName="Image" time="98086088" x="0" y="105" width="640" height="19" visible="true" fillParentWidth="false" fillParentHeight="false" nodeAlign="1" file="common/decoration/line.png" packFile="" gridLeft="0" gridRight="0" gridTop="0" gridBottom="0"/><close_btn type="2" typeName="Button" time="102139208" x="42" y="39" width="60" height="60" visible="true" fillParentWidth="false" fillParentHeight="false" nodeAlign="2" file="common/button/btn_close.png" file2="" packFile="" gridLeft="0" gridRight="0" gridTop="0" gridBottom="0"/></bg></root>
