<?xml version="1.0" encoding="utf-8"?>
<root type="0" typeName="View" time="0" x="0" y="0" width="0" height="0" visible="true" fillParentWidth="true" fillParentHeight="true" nodeAlign="0"><bg type="1" typeName="Image" time="120301323" x="0" y="0" width="720" height="1046" visible="true" fillParentWidth="false" fillParentHeight="false" nodeAlign="5" file="common/background/dialog_bg_1.png" packFile="" gridLeft="128" gridRight="128" gridTop="128" gridBottom="128"><line type="1" typeName="Image" time="120301391" x="0" y="116" width="630" height="19" visible="true" fillParentWidth="false" fillParentHeight="false" nodeAlign="1" file="common/decoration/line.png" packFile="" gridLeft="0" gridRight="0" gridTop="0" gridBottom="0"/><title type="4" typeName="Text" time="120301441" x="0" y="0" width="200" height="150" visible="true" fillParentWidth="false" fillParentHeight="false" nodeAlign="1" fontSize="40" textAlign="0" color="0x505050" string="收到互动物品"/><list_view type="0" typeName="View" time="120301509" x="0" y="300" width="648" height="716" visible="true" fillParentWidth="false" fillParentHeight="false" nodeAlign="1"><bg_line type="1" typeName="Image" time="129092985" x="0" y="8" width="640" height="700" visible="true" fillParentWidth="false" fillParentHeight="false" nodeAlign="1" file="common/background/line_bg.png" packFile="" gridLeft="64" gridRight="64" gridTop="64" gridBottom="64"/><top_title_view type="0" typeName="View" time="129093349" x="0" y="0" width="600" height="86" visible="true" fillParentWidth="false" fillParentHeight="false" nodeAlign="1"><Image5 type="1" typeName="Image" time="129093080" x="3" y="0" width="134" height="2" visible="true" fillParentWidth="false" fillParentHeight="false" nodeAlign="7" file="relation/cloud_line.png" packFile="" gridLeft="0" gridRight="0" gridTop="0" gridBottom="0"/><Image51 type="1" typeName="Image" time="129093474" x="3" y="0" width="134" height="2" visible="true" fillParentWidth="false" fillParentHeight="false" nodeAlign="3" file="relation/cloud_line.png" packFile="" gridLeft="0" gridRight="0" gridTop="0" gridBottom="0"/><Image6 type="1" typeName="Image" time="129093624" x="136" y="0" width="28" height="20" visible="true" fillParentWidth="false" fillParentHeight="false" nodeAlign="3" file="relation/l_cloud.png" packFile="" gridLeft="0" gridRight="0" gridTop="0" gridBottom="0"/><Image61 type="1" typeName="Image" time="129093672" x="136" y="0" width="28" height="20" visible="true" fillParentWidth="false" fillParentHeight="false" nodeAlign="7" file="relation/r_cloud.png" packFile="" gridLeft="0" gridRight="0" gridTop="0" gridBottom="0"/><title type="4" typeName="Text" time="129093684" x="0" y="28" width="200" height="0" visible="true" fillParentWidth="false" fillParentHeight="false" nodeAlign="1" fontSize="28" textAlign="0" color="0x5F6487" string="本周最活跃互动棋友"/></top_title_view><rank_view type="0" typeName="View" time="129093814" x="0" y="54" width="604" height="641" visible="true" fillParentWidth="false" fillParentHeight="false" nodeAlign="1"/><tips type="4" typeName="Text" time="129799339" x="0" y="-16" width="200" height="0" visible="false" fillParentWidth="false" fillParentHeight="false" nodeAlign="0" fontSize="30" textAlign="0" color="0x787878" string="大侠，您本周还没有收到互动道具哦~"/></list_view><item_view type="0" typeName="View" time="129091447" x="-30" y="130" width="560" height="136" visible="true" fillParentWidth="false" fillParentHeight="false" nodeAlign="1"/></bg></root>
