<?xml version="1.0" encoding="utf-8"?>
<new_style_view type="0" typeName="View" time="143948048" x="171" y="245" width="200" height="150" visible="true" fillParentWidth="true" fillParentHeight="true" nodeAlign="8"><bg_img type="1" typeName="Image" time="143805486" x="0" y="0" width="720" height="1280" visible="true" fillParentWidth="true" fillParentHeight="true" nodeAlign="8" file="drawable/blank_black.png" packFile="" gridLeft="0" gridRight="0" gridTop="0" gridBottom="0"/><title_view type="0" typeName="View" time="143805615" x="0" y="0" width="480" height="95" visible="true" fillParentWidth="true" fillParentHeight="false" nodeAlign="1"><title_bg_img type="1" typeName="Image" time="143805662" x="0" y="0" width="720" height="116" visible="true" fillParentWidth="true" fillParentHeight="false" nodeAlign="1" file="common/background/chat_title_bg.png" packFile="" gridLeft="0" gridRight="0" gridTop="0" gridBottom="0"/><title_tx type="4" typeName="Text" time="143805787" x="0" y="0" width="96" height="48" visible="true" fillParentWidth="false" fillParentHeight="false" nodeAlign="0" fontSize="48" textAlign="0" color="0xA0C8E1" string=""/></title_view><topright_btn type="2" typeName="Button" time="143805964" x="34" y="21" width="60" height="60" visible="true" fillParentWidth="false" fillParentHeight="false" nodeAlign="2" file="common/icon/gift_icon.png" file2="" packFile="" gridLeft="0" gridRight="0" gridTop="0" gridBottom="0"/><back_btn type="2" typeName="Button" time="143806053" x="27" y="36" width="60" height="60" visible="true" fillParentWidth="false" fillParentHeight="false" nodeAlign="6" file="common/button/hide_dialog_btn.png" file2="" packFile="" gridLeft="0" gridRight="0" gridTop="0" gridBottom="0"/><bottom_btn type="2" typeName="Button" time="143806107" x="0" y="19" width="444" height="96" visible="true" fillParentWidth="false" fillParentHeight="false" nodeAlign="5" file="common/button/long_yellow_btn.png" file2="" packFile="" gridLeft="0" gridRight="0" gridTop="0" gridBottom="0"><bottom_btn_tx type="4" typeName="Text" time="143806200" x="0" y="0" width="144" height="36" visible="true" fillParentWidth="false" fillParentHeight="false" nodeAlign="0" fontSize="36" textAlign="0" color="0x0F0F5F" string=""/></bottom_btn><content_view type="0" typeName="View" time="143806374" x="0" y="128" width="720" height="1025" visible="true" fillParentWidth="false" fillParentHeight="false" nodeAlign="1"/></new_style_view>
